Metadata-Version: 2.1
Name: lyric-matcher
Version: 0.0.8
Summary: README.md
Home-page: UNKNOWN
Author: hanhaodi zhang, zhaoyang bu
Author-email: 1004591463@qq.com
License: UNKNOWN
Platform: UNKNOWN
Classifier: Programming Language :: Python :: 3
Classifier: License :: OSI Approved :: MIT License
Classifier: Operating System :: OS Independent
